meg_qc/__init__.py
meg_qc/__main__.py
meg_qc/_version.py
meg_qc/create_plots.py
meg_qc/get_config.py
meg_qc/run_megqc.py
meg_qc/test.py
meg_qc/calculation/between_sample_analysis.py
meg_qc/calculation/initial_meg_qc.py
meg_qc/calculation/meg_qc_pipeline.py
meg_qc/calculation/objects.py
meg_qc/calculation/metrics/ECG_EOG_meg_qc.py
meg_qc/calculation/metrics/Head_meg_qc.py
meg_qc/calculation/metrics/PSD_meg_qc.py
meg_qc/calculation/metrics/Peaks_auto_meg_qc.py
meg_qc/calculation/metrics/Peaks_manual_meg_qc.py
meg_qc/calculation/metrics/Peaks_manual_meg_qc_numba.py
meg_qc/calculation/metrics/STD_meg_qc.py
meg_qc/calculation/metrics/muscle_meg_qc.py
meg_qc/calculation/metrics/summary_report_GQI.py
meg_qc/miscellaneous/GUI/logo.png
meg_qc/miscellaneous/GUI/megqcGUI.py
meg_qc/miscellaneous/GUI/worker_entry.py
meg_qc/miscellaneous/examples/run_calculation_module.py
meg_qc/miscellaneous/examples/run_plotting_module.py
meg_qc/miscellaneous/optimizations/artifact_detection_ancp.py
meg_qc/plotting/meg_qc_plots.py
meg_qc/plotting/universal_html_report.py
meg_qc/plotting/universal_plots.py
meg_qc/plotting/universal_plots_lite.py
meg_qc/settings/settings.ini
meg_qc/settings/settings_internal.ini
meg_qc-0.6.7.dist-info/licenses/LICENSE
meg_qc-0.6.7.dist-info/METADATA
meg_qc-0.6.7.dist-info/WHEEL
meg_qc-0.6.7.dist-info/entry_points.txt
meg_qc-0.6.7.dist-info/top_level.txt
meg_qc-0.6.7.dist-info/RECORD
