Metadata-Version: 2.4
Name: meg_qc
Version: 0.6.7
Summary: Tool for automated MEG data quality control
Author: Karel Lopez Vilaret, Evgeniia Gapontseva, Aaron Reer, Jorge Bosch, Erdal Karaca
Author-email: Karel Lopez Vilaret <karel.mauricio.lopez.vilaret@uni-oldenburg.de>
Maintainer-email: "ANCP Lab, University of Oldenburg" <currentancp@listserv.uni-oldenburg.de>
License: MIT
Project-URL: Homepage, https://github.com/ANCPLabOldenburg/MEGqc
Classifier: Development Status :: 3 - Alpha
Classifier: Environment :: Console
Classifier: Intended Audience :: Science/Research
Classifier: License :: OSI Approved :: MIT License
Classifier: Operating System :: OS Independent
Classifier: Programming Language :: Python :: 3.8
Classifier: Programming Language :: Python :: 3.9
Classifier: Programming Language :: Python :: 3.10
Classifier: Programming Language :: Python :: 3.11
Classifier: Programming Language :: Python :: 3.12
Classifier: Programming Language :: Python :: 3.13
Classifier: Programming Language :: Python :: 3.14
Classifier: Topic :: Scientific/Engineering
Requires-Python: >=3.9
License-File: LICENSE
Requires-Dist: ancpbids==0.3.0
Requires-Dist: prompt_toolkit==3.0.48
Requires-Dist: mne~=1.6.0
Requires-Dist: pandas>=2.0.3
Requires-Dist: plotly==5.24.1
Requires-Dist: joblib==1.4.2
Requires-Dist: pyqt6
Requires-Dist: pyqt6-plugins==6.4.2.2.3; platform_system != "Darwin"
Requires-Dist: numba==0.58.1
Requires-Dist: psutil==5.9.8
Requires-Dist: matplotlib==3.8.4
Requires-Dist: statsmodels
Requires-Dist: scikit-learn
Requires-Dist: seaborn
Dynamic: license-file
